geoip.py
python_geoip_python3-1.3.dist-info/DESCRIPTION.rst
python_geoip_python3-1.3.dist-info/METADATA
python_geoip_python3-1.3.dist-info/metadata.json
python_geoip_python3-1.3.dist-info/RECORD
python_geoip_python3-1.3.dist-info/top_level.txt
python_geoip_python3-1.3.dist-info/WHEEL
