Metadata-Version: 1.1
Name: python-geoip-python3
Version: 1.3
Summary: Provides GeoIP functionality for Python.
Home-page: https://github.com/richardasaurus/python-geoip-python3
Author: Richard O'Dwyer
Author-email: richard@richard.do
License: UNKNOWN
Platform: UNKNOWN
Classifier: Programming Language :: Python
Classifier: Programming Language :: Python :: 2
Classifier: Programming Language :: Python :: 2.6
Classifier: Programming Language :: Python :: 2.7
Classifier: Programming Language :: Python :: 3
Classifier: Programming Language :: Python :: 3.3
Classifier: Programming Language :: Python :: 3.4
Classifier: License :: OSI Approved :: BSD License
